xontrib_pyenv/__init__.py
xontrib_pyenv-1.1.0.dist-info/LICENSE
xontrib_pyenv-1.1.0.dist-info/WHEEL
xontrib_pyenv-1.1.0.dist-info/METADATA
xontrib_pyenv-1.1.0.dist-info/RECORD
